{"ImageURL": "https://rohitfarmer.github.io/bioinfobot/images/2021-01.png", "TopWords": [["one", 879], ["time", 695], ["data", 548], ["covid", 533], ["year", 484], ["first", 467], ["know", 466], ["need", 448], ["think", 445], ["still", 438], ["really", 430], ["many", 422], ["much", 380], ["well", 379], ["going", 372], ["back", 338], ["research", 338], ["years", 335], ["way", 334], ["science", 333]], "TweetCount": 17249, "TotalWords": 180850, "UniqueWords": 31510, "HashFreq": [["#covid19", 258], ["#bioinformatics", 160], ["#genomics", 150], ["#sarscov2", 85], ["#ai", 51], ["#rstats", 50], ["#scicomm", 47], ["#paper", 45], ["#datascience", 43], ["#science", 41], ["#microbiome", 38], ["#cancer", 37], ["#fog2021", 37], ["#academictwitter", 35], ["#genetics", 35], ["#openscience", 31], ["#academicchatter", 30], ["#biotechnology", 30], ["#rna", 29], ["#ngs", 29]], "UsersFreq": [["halvorz", 256], ["nope_its_lily", 220], ["cdanielleadams", 212], ["27CansOfTuna", 199], ["rnomics", 129], ["stuffysour", 118], ["Kevin_McKernan", 117], ["ivan_bezdomny", 109], ["daumari", 109], ["thebiologistisn", 108], ["DamCou", 105], ["Primary_Immune", 105], ["annie_dibz", 101], ["KirkegaardEmil", 99], ["EmmanuelNaouri", 99], ["Sanyiikoo_Oromo", 90], ["YoungChris27040", 90], ["jsantoyo", 89], ["jbadomics", 85], ["wakehamAMR", 84]], "PopularLanguages": [["Python", 8], ["Bioconductor", 3], ["R", 2], ["C", 1], ["Groovy", 1], ["Hack", 1], ["JavaScript", 1], ["Rust", 1]]}